grammar_gpt/__init__.py
grammar_gpt/engine.py
grammar_gpt/lang.py
grammar_gpt-0.0.2.dist-info/LICENSE
grammar_gpt-0.0.2.dist-info/WHEEL
grammar_gpt-0.0.2.dist-info/METADATA
grammar_gpt-0.0.2.dist-info/RECORD
